<?xml version="1.0" encoding="UTF-8"?>
<export version="E">
  <design>
    <source>C:\Users\hamster\Documents\Development\dczia\Ziacon2\yolo-badge.kicad_sch</source>
    <date>4/16/2021 11:26:57 PM</date>
    <tool>Eeschema (5.99.0-10336-g9846076676)</tool>
    <sheet number="1" name="/" tstamps="/">
      <title_block>
        <title/>
        <company/>
        <rev/>
        <date/>
        <source>yolo-badge.kicad_sch</source>
        <comment number="1" value=""/>
        <comment number="2" value=""/>
        <comment number="3" value=""/>
        <comment number="4" value=""/>
        <comment number="5" value=""/>
        <comment number="6" value=""/>
        <comment number="7" value=""/>
        <comment number="8" value=""/>
        <comment number="9" value=""/>
      </title_block>
    </sheet>
  </design>
  <components>
    <comp ref="C1">
      <value>10uF</value>
      <footprint>Capacitor_SMD:C_0603_1608Metric</footprint>
      <datasheet>~</datasheet>
      <libsource lib="Device" part="C" description="Unpolarized capacitor"/>
      <property name="Sheetname" value=""/>
      <property name="Sheetfile" value="yolo-badge.kicad_sch"/>
      <sheetpath names="/" tstamps="/"/>
      <tstamps>00000000-0000-0000-0000-00005b849620</tstamps>
    </comp>
    <comp ref="C2">
      <value>0.1uF</value>
      <footprint>Capacitor_SMD:C_0603_1608Metric</footprint>
      <datasheet>~</datasheet>
      <libsource lib="Device" part="C" description="Unpolarized capacitor"/>
      <property name="Sheetname" value=""/>
      <property name="Sheetfile" value="yolo-badge.kicad_sch"/>
      <sheetpath names="/" tstamps="/"/>
      <tstamps>00000000-0000-0000-0000-00005b845710</tstamps>
    </comp>
    <comp ref="C3">
      <value>0.1uF</value>
      <footprint>Capacitor_SMD:C_0603_1608Metric</footprint>
      <datasheet>~</datasheet>
      <libsource lib="Device" part="C" description="Unpolarized capacitor"/>
      <property name="Sheetname" value=""/>
      <property name="Sheetfile" value="yolo-badge.kicad_sch"/>
      <sheetpath names="/" tstamps="/"/>
      <tstamps>00000000-0000-0000-0000-00005b847476</tstamps>
    </comp>
    <comp ref="C4">
      <value>1uF</value>
      <footprint>Capacitor_SMD:C_0603_1608Metric</footprint>
      <datasheet>~</datasheet>
      <libsource lib="Device" part="C" description="Unpolarized capacitor"/>
      <property name="Sheetname" value=""/>
      <property name="Sheetfile" value="yolo-badge.kicad_sch"/>
      <sheetpath names="/" tstamps="/"/>
      <tstamps>00000000-0000-0000-0000-00005b83ef33</tstamps>
    </comp>
    <comp ref="C5">
      <value>12pF</value>
      <footprint>Capacitor_SMD:C_0603_1608Metric</footprint>
      <datasheet>~</datasheet>
      <libsource lib="Device" part="C" description="Unpolarized capacitor"/>
      <property name="Sheetname" value=""/>
      <property name="Sheetfile" value="yolo-badge.kicad_sch"/>
      <sheetpath names="/" tstamps="/"/>
      <tstamps>00000000-0000-0000-0000-00005b83f1fe</tstamps>
    </comp>
    <comp ref="C6">
      <value>12pF</value>
      <footprint>Capacitor_SMD:C_0603_1608Metric</footprint>
      <datasheet>~</datasheet>
      <libsource lib="Device" part="C" description="Unpolarized capacitor"/>
      <property name="Sheetname" value=""/>
      <property name="Sheetfile" value="yolo-badge.kicad_sch"/>
      <sheetpath names="/" tstamps="/"/>
      <tstamps>00000000-0000-0000-0000-00005b83f829</tstamps>
    </comp>
    <comp ref="D1">
      <value>WS2812B</value>
      <footprint>LED_SMD:LED_WS2812B_PLCC4_5.0x5.0mm_P3.2mm</footprint>
      <datasheet>https://cdn-shop.adafruit.com/datasheets/WS2812B.pdf</datasheet>
      <libsource lib="LED" part="WS2812B" description="RGB LED with integrated controller"/>
      <property name="Sheetname" value=""/>
      <property name="Sheetfile" value="yolo-badge.kicad_sch"/>
      <sheetpath names="/" tstamps="/"/>
      <tstamps>cc4ddf90-0893-4d77-8e5e-ffc436c2e84e</tstamps>
    </comp>
    <comp ref="D2">
      <value>WS2812B</value>
      <footprint>LED_SMD:LED_WS2812B_PLCC4_5.0x5.0mm_P3.2mm</footprint>
      <datasheet>https://cdn-shop.adafruit.com/datasheets/WS2812B.pdf</datasheet>
      <libsource lib="LED" part="WS2812B" description="RGB LED with integrated controller"/>
      <property name="Sheetname" value=""/>
      <property name="Sheetfile" value="yolo-badge.kicad_sch"/>
      <sheetpath names="/" tstamps="/"/>
      <tstamps>5202fafe-cd9c-4dc3-87f1-5eb98416818f</tstamps>
    </comp>
    <comp ref="D3">
      <value>WS2812B</value>
      <footprint>LED_SMD:LED_WS2812B_PLCC4_5.0x5.0mm_P3.2mm</footprint>
      <datasheet>https://cdn-shop.adafruit.com/datasheets/WS2812B.pdf</datasheet>
      <libsource lib="LED" part="WS2812B" description="RGB LED with integrated controller"/>
      <property name="Sheetname" value=""/>
      <property name="Sheetfile" value="yolo-badge.kicad_sch"/>
      <sheetpath names="/" tstamps="/"/>
      <tstamps>60b70461-77e0-4453-baaf-149788588aef</tstamps>
    </comp>
    <comp ref="D4">
      <value>WS2812B</value>
      <footprint>LED_SMD:LED_WS2812B_PLCC4_5.0x5.0mm_P3.2mm</footprint>
      <datasheet>https://cdn-shop.adafruit.com/datasheets/WS2812B.pdf</datasheet>
      <libsource lib="LED" part="WS2812B" description="RGB LED with integrated controller"/>
      <property name="Sheetname" value=""/>
      <property name="Sheetfile" value="yolo-badge.kicad_sch"/>
      <sheetpath names="/" tstamps="/"/>
      <tstamps>83904ae2-346e-420e-b819-d16e63c1fed0</tstamps>
    </comp>
    <comp ref="D5">
      <value>WS2812B</value>
      <footprint>LED_SMD:LED_WS2812B_PLCC4_5.0x5.0mm_P3.2mm</footprint>
      <datasheet>https://cdn-shop.adafruit.com/datasheets/WS2812B.pdf</datasheet>
      <libsource lib="LED" part="WS2812B" description="RGB LED with integrated controller"/>
      <property name="Sheetname" value=""/>
      <property name="Sheetfile" value="yolo-badge.kicad_sch"/>
      <sheetpath names="/" tstamps="/"/>
      <tstamps>740852eb-4b7c-498a-9280-54ee5bf3386a</tstamps>
    </comp>
    <comp ref="D6">
      <value>WS2812B</value>
      <footprint>LED_SMD:LED_WS2812B_PLCC4_5.0x5.0mm_P3.2mm</footprint>
      <datasheet>https://cdn-shop.adafruit.com/datasheets/WS2812B.pdf</datasheet>
      <libsource lib="LED" part="WS2812B" description="RGB LED with integrated controller"/>
      <property name="Sheetname" value=""/>
      <property name="Sheetfile" value="yolo-badge.kicad_sch"/>
      <sheetpath names="/" tstamps="/"/>
      <tstamps>25e46214-f4c0-4bfc-93a1-1041ca8cd07a</tstamps>
    </comp>
    <comp ref="D7">
      <value>WS2812B</value>
      <footprint>LED_SMD:LED_WS2812B_PLCC4_5.0x5.0mm_P3.2mm</footprint>
      <datasheet>https://cdn-shop.adafruit.com/datasheets/WS2812B.pdf</datasheet>
      <libsource lib="LED" part="WS2812B" description="RGB LED with integrated controller"/>
      <property name="Sheetname" value=""/>
      <property name="Sheetfile" value="yolo-badge.kicad_sch"/>
      <sheetpath names="/" tstamps="/"/>
      <tstamps>30c3e2d3-caf9-41f3-b790-06e206eccf2f</tstamps>
    </comp>
    <comp ref="D8">
      <value>WS2812B</value>
      <footprint>LED_SMD:LED_WS2812B_PLCC4_5.0x5.0mm_P3.2mm</footprint>
      <datasheet>https://cdn-shop.adafruit.com/datasheets/WS2812B.pdf</datasheet>
      <libsource lib="LED" part="WS2812B" description="RGB LED with integrated controller"/>
      <property name="Sheetname" value=""/>
      <property name="Sheetfile" value="yolo-badge.kicad_sch"/>
      <sheetpath names="/" tstamps="/"/>
      <tstamps>630b67a1-c14f-4808-946a-4b509a487b77</tstamps>
    </comp>
    <comp ref="D9">
      <value>WS2812B</value>
      <footprint>LED_SMD:LED_WS2812B_PLCC4_5.0x5.0mm_P3.2mm</footprint>
      <datasheet>https://cdn-shop.adafruit.com/datasheets/WS2812B.pdf</datasheet>
      <libsource lib="LED" part="WS2812B" description="RGB LED with integrated controller"/>
      <property name="Sheetname" value=""/>
      <property name="Sheetfile" value="yolo-badge.kicad_sch"/>
      <sheetpath names="/" tstamps="/"/>
      <tstamps>c75a5206-d4dd-4102-9030-5f44ae33d984</tstamps>
    </comp>
    <comp ref="D10">
      <value>WS2812B</value>
      <footprint>LED_SMD:LED_WS2812B_PLCC4_5.0x5.0mm_P3.2mm</footprint>
      <datasheet>https://cdn-shop.adafruit.com/datasheets/WS2812B.pdf</datasheet>
      <libsource lib="LED" part="WS2812B" description="RGB LED with integrated controller"/>
      <property name="Sheetname" value=""/>
      <property name="Sheetfile" value="yolo-badge.kicad_sch"/>
      <sheetpath names="/" tstamps="/"/>
      <tstamps>cc2962f2-3aa7-48c0-baf7-962848384d41</tstamps>
    </comp>
    <comp ref="D11">
      <value>Status</value>
      <footprint>LED_SMD:LED_0603_1608Metric</footprint>
      <datasheet>~</datasheet>
      <libsource lib="Device" part="LED" description="Light emitting diode"/>
      <property name="Sheetname" value=""/>
      <property name="Sheetfile" value="yolo-badge.kicad_sch"/>
      <sheetpath names="/" tstamps="/"/>
      <tstamps>00000000-0000-0000-0000-00005b85dbd2</tstamps>
    </comp>
    <comp ref="J1">
      <value>SPI</value>
      <footprint>Connector_PinHeader_2.54mm:PinHeader_2x03_P2.54mm_Vertical</footprint>
      <datasheet>~</datasheet>
      <libsource lib="Connector_Generic" part="Conn_02x03_Odd_Even" description="Generic connector, double row, 02x03, odd/even pin numbering scheme (row 1 odd numbers, row 2 even numbers), script generated (kicad-library-utils/schlib/autogen/connector/)"/>
      <property name="Sheetname" value=""/>
      <property name="Sheetfile" value="yolo-badge.kicad_sch"/>
      <sheetpath names="/" tstamps="/"/>
      <tstamps>00000000-0000-0000-0000-00005b841550</tstamps>
    </comp>
    <comp ref="J2">
      <value>USB_B_Micro</value>
      <footprint>Connector_USB:USB_Micro-B_Molex_47346-0001</footprint>
      <datasheet>~</datasheet>
      <libsource lib="programmer-rescue" part="USB_B_Micro-Connector_Specialized" description=""/>
      <property name="Sheetname" value=""/>
      <property name="Sheetfile" value="yolo-badge.kicad_sch"/>
      <sheetpath names="/" tstamps="/"/>
      <tstamps>00000000-0000-0000-0000-00005b83e55a</tstamps>
    </comp>
    <comp ref="JP3">
      <value>Bootloader</value>
      <footprint>Jumper:SolderJumper-2_P1.3mm_Open_RoundedPad1.0x1.5mm</footprint>
      <datasheet>~</datasheet>
      <libsource lib="Jumper" part="SolderJumper_2_Open" description="Solder Jumper, 2-pole, open"/>
      <property name="Sheetname" value=""/>
      <property name="Sheetfile" value="yolo-badge.kicad_sch"/>
      <sheetpath names="/" tstamps="/"/>
      <tstamps>00000000-0000-0000-0000-00005d290119</tstamps>
    </comp>
    <comp ref="R3">
      <value>22R</value>
      <footprint>Resistor_SMD:R_0603_1608Metric</footprint>
      <datasheet>~</datasheet>
      <libsource lib="Device" part="R" description="Resistor"/>
      <property name="Sheetname" value=""/>
      <property name="Sheetfile" value="yolo-badge.kicad_sch"/>
      <sheetpath names="/" tstamps="/"/>
      <tstamps>00000000-0000-0000-0000-00005b83e61a</tstamps>
    </comp>
    <comp ref="R4">
      <value>22R</value>
      <footprint>Resistor_SMD:R_0603_1608Metric</footprint>
      <datasheet>~</datasheet>
      <libsource lib="Device" part="R" description="Resistor"/>
      <property name="Sheetname" value=""/>
      <property name="Sheetfile" value="yolo-badge.kicad_sch"/>
      <sheetpath names="/" tstamps="/"/>
      <tstamps>00000000-0000-0000-0000-00005b83e748</tstamps>
    </comp>
    <comp ref="R5">
      <value>10k</value>
      <footprint>Resistor_SMD:R_0603_1608Metric</footprint>
      <datasheet>~</datasheet>
      <libsource lib="Device" part="R" description="Resistor"/>
      <property name="Sheetname" value=""/>
      <property name="Sheetfile" value="yolo-badge.kicad_sch"/>
      <sheetpath names="/" tstamps="/"/>
      <tstamps>00000000-0000-0000-0000-00005b869212</tstamps>
    </comp>
    <comp ref="R6">
      <value>330R</value>
      <footprint>Resistor_SMD:R_0603_1608Metric</footprint>
      <datasheet>~</datasheet>
      <libsource lib="Device" part="R" description="Resistor"/>
      <property name="Sheetname" value=""/>
      <property name="Sheetfile" value="yolo-badge.kicad_sch"/>
      <sheetpath names="/" tstamps="/"/>
      <tstamps>00000000-0000-0000-0000-00005b85de62</tstamps>
    </comp>
    <comp ref="R7">
      <value>10k</value>
      <footprint>Resistor_SMD:R_0603_1608Metric</footprint>
      <datasheet>~</datasheet>
      <libsource lib="Device" part="R" description="Resistor"/>
      <property name="Sheetname" value=""/>
      <property name="Sheetfile" value="yolo-badge.kicad_sch"/>
      <sheetpath names="/" tstamps="/"/>
      <tstamps>00000000-0000-0000-0000-00005d2a823d</tstamps>
    </comp>
    <comp ref="RX1">
      <value>Test_Point</value>
      <footprint>TestPoint:TestPoint_Pad_2.0x2.0mm</footprint>
      <datasheet>~</datasheet>
      <libsource lib="programmer-rescue" part="Test_Point-Connector_Specialized" description=""/>
      <property name="Sheetname" value=""/>
      <property name="Sheetfile" value="yolo-badge.kicad_sch"/>
      <sheetpath names="/" tstamps="/"/>
      <tstamps>00000000-0000-0000-0000-00005b8cf18b</tstamps>
    </comp>
    <comp ref="SW1">
      <value>SW_Push</value>
      <footprint>lip_fp:Wurth_434331013822</footprint>
      <libsource lib="Switch" part="SW_Push" description="Push button switch, generic, two pins"/>
      <property name="Sheetname" value=""/>
      <property name="Sheetfile" value="yolo-badge.kicad_sch"/>
      <sheetpath names="/" tstamps="/"/>
      <tstamps>00000000-0000-0000-0000-00005b8832d1</tstamps>
    </comp>
    <comp ref="TX1">
      <value>Test_Point</value>
      <footprint>TestPoint:TestPoint_Pad_2.0x2.0mm</footprint>
      <datasheet>~</datasheet>
      <libsource lib="programmer-rescue" part="Test_Point-Connector_Specialized" description=""/>
      <property name="Sheetname" value=""/>
      <property name="Sheetfile" value="yolo-badge.kicad_sch"/>
      <sheetpath names="/" tstamps="/"/>
      <tstamps>00000000-0000-0000-0000-00005b8cf2a2</tstamps>
    </comp>
    <comp ref="U1">
      <value>TPS73233DBVT</value>
      <footprint>Package_TO_SOT_SMD:SOT-23-5</footprint>
      <datasheet>1.02 USD</datasheet>
      <fields>
        <field name="Field4">SOT-23-5 Texas Instruments</field>
        <field name="Field5">TPS73233DBVT</field>
        <field name="Field7">Texas Instruments</field>
        <field name="Field8">Cap-Free, NMOS, 250mA Low Dropout Regulator with Reverse Current Protection 5-SOT-23 -40 to 125</field>
      </fields>
      <libsource lib="TPS73233DBVT" part="TPS73233DBVT" description=""/>
      <property name="Field4" value="SOT-23-5 Texas Instruments"/>
      <property name="Field5" value="TPS73233DBVT"/>
      <property name="Field7" value="Texas Instruments"/>
      <property name="Field8" value="Cap-Free, NMOS, 250mA Low Dropout Regulator with Reverse Current Protection 5-SOT-23 -40 to 125"/>
      <property name="Sheetname" value=""/>
      <property name="Sheetfile" value="yolo-badge.kicad_sch"/>
      <sheetpath names="/" tstamps="/"/>
      <tstamps>00000000-0000-0000-0000-00005b8430e0</tstamps>
    </comp>
    <comp ref="U2">
      <value>ATmega32U4-AU</value>
      <footprint>Package_QFP:TQFP-44_10x10mm_P0.8mm</footprint>
      <datasheet>http://ww1.microchip.com/downloads/en/DeviceDoc/Atmel-7766-8-bit-AVR-ATmega16U4-32U4_Datasheet.pdf</datasheet>
      <libsource lib="programmer-rescue" part="ATmega32U4-AU-MCU_Microchip_ATmega" description=""/>
      <property name="Sheetname" value=""/>
      <property name="Sheetfile" value="yolo-badge.kicad_sch"/>
      <sheetpath names="/" tstamps="/"/>
      <tstamps>00000000-0000-0000-0000-00005b83e47b</tstamps>
    </comp>
    <comp ref="X1">
      <value>Badgelife_sao_connector_v169bis</value>
      <footprint>lip_fp:Badgelife-Shitty-v1.69bis</footprint>
      <libsource lib="badgelife_shitty_addon_v169bis" part="Badgelife_sao_connector_v169bis" description=""/>
      <property name="Sheetname" value=""/>
      <property name="Sheetfile" value="yolo-badge.kicad_sch"/>
      <sheetpath names="/" tstamps="/"/>
      <tstamps>00000000-0000-0000-0000-00005d2cdb5c</tstamps>
    </comp>
    <comp ref="Y1">
      <value>16Mhz</value>
      <footprint>Crystal:Crystal_SMD_HC49-SD</footprint>
      <datasheet>~</datasheet>
      <libsource lib="Device" part="Crystal" description="Two pin crystal"/>
      <property name="Sheetname" value=""/>
      <property name="Sheetfile" value="yolo-badge.kicad_sch"/>
      <sheetpath names="/" tstamps="/"/>
      <tstamps>00000000-0000-0000-0000-00005b83f37b</tstamps>
    </comp>
  </components>
  <libparts>
    <libpart lib="Connector_Generic" part="Conn_02x03_Odd_Even">
      <description>Generic connector, double row, 02x03, odd/even pin numbering scheme (row 1 odd numbers, row 2 even numbers), script generated (kicad-library-utils/schlib/autogen/connector/)</description>
      <docs>~</docs>
      <footprints>
        <fp>Connector*:*_2x??_*</fp>
      </footprints>
      <fields>
        <field name="Reference">J</field>
        <field name="Value">Conn_02x03_Odd_Even</field>
        <field name="Datasheet">~</field>
      </fields>
      <pins>
        <pin num="1" name="Pin_1" type="passive"/>
        <pin num="2" name="Pin_2" type="passive"/>
        <pin num="3" name="Pin_3" type="passive"/>
        <pin num="4" name="Pin_4" type="passive"/>
        <pin num="5" name="Pin_5" type="passive"/>
        <pin num="6" name="Pin_6" type="passive"/>
      </pins>
    </libpart>
    <libpart lib="Device" part="C">
      <description>Unpolarized capacitor</description>
      <docs>~</docs>
      <footprints>
        <fp>C_*</fp>
      </footprints>
      <fields>
        <field name="Reference">C</field>
        <field name="Value">C</field>
        <field name="Datasheet">~</field>
      </fields>
      <pins>
        <pin num="1" name="~" type="passive"/>
        <pin num="2" name="~" type="passive"/>
      </pins>
    </libpart>
    <libpart lib="Device" part="Crystal">
      <description>Two pin crystal</description>
      <docs>~</docs>
      <footprints>
        <fp>Crystal*</fp>
      </footprints>
      <fields>
        <field name="Reference">Y</field>
        <field name="Value">Crystal</field>
        <field name="Datasheet">~</field>
      </fields>
      <pins>
        <pin num="1" name="1" type="passive"/>
        <pin num="2" name="2" type="passive"/>
      </pins>
    </libpart>
    <libpart lib="Device" part="LED">
      <description>Light emitting diode</description>
      <docs>~</docs>
      <footprints>
        <fp>LED*</fp>
        <fp>LED_SMD:*</fp>
        <fp>LED_THT:*</fp>
      </footprints>
      <fields>
        <field name="Reference">D</field>
        <field name="Value">LED</field>
        <field name="Datasheet">~</field>
      </fields>
      <pins>
        <pin num="1" name="K" type="passive"/>
        <pin num="2" name="A" type="passive"/>
      </pins>
    </libpart>
    <libpart lib="Device" part="R">
      <description>Resistor</description>
      <docs>~</docs>
      <footprints>
        <fp>R_*</fp>
      </footprints>
      <fields>
        <field name="Reference">R</field>
        <field name="Value">R</field>
        <field name="Datasheet">~</field>
      </fields>
      <pins>
        <pin num="1" name="~" type="passive"/>
        <pin num="2" name="~" type="passive"/>
      </pins>
    </libpart>
    <libpart lib="Jumper" part="SolderJumper_2_Open">
      <description>Solder Jumper, 2-pole, open</description>
      <docs>~</docs>
      <footprints>
        <fp>SolderJumper*Open*</fp>
      </footprints>
      <fields>
        <field name="Reference">JP</field>
        <field name="Value">SolderJumper_2_Open</field>
        <field name="Datasheet">~</field>
      </fields>
      <pins>
        <pin num="1" name="A" type="passive"/>
        <pin num="2" name="B" type="passive"/>
      </pins>
    </libpart>
    <libpart lib="LED" part="WS2812B">
      <description>RGB LED with integrated controller</description>
      <docs>https://cdn-shop.adafruit.com/datasheets/WS2812B.pdf</docs>
      <footprints>
        <fp>LED*WS2812*PLCC*5.0x5.0mm*P3.2mm*</fp>
      </footprints>
      <fields>
        <field name="Reference">D</field>
        <field name="Value">WS2812B</field>
        <field name="Footprint">LED_SMD:LED_WS2812B_PLCC4_5.0x5.0mm_P3.2mm</field>
        <field name="Datasheet">https://cdn-shop.adafruit.com/datasheets/WS2812B.pdf</field>
      </fields>
      <pins>
        <pin num="1" name="VDD" type="power_in"/>
        <pin num="2" name="DOUT" type="output"/>
        <pin num="3" name="VSS" type="power_in"/>
        <pin num="4" name="DIN" type="input"/>
      </pins>
    </libpart>
    <libpart lib="Switch" part="SW_Push">
      <description>Push button switch, generic, two pins</description>
      <docs>~</docs>
      <fields>
        <field name="Reference">SW</field>
        <field name="Value">SW_Push</field>
        <field name="Datasheet">~</field>
      </fields>
      <pins>
        <pin num="1" name="1" type="passive"/>
        <pin num="2" name="2" type="passive"/>
      </pins>
    </libpart>
    <libpart lib="TPS73233DBVT" part="TPS73233DBVT">
      <docs>1.02 USD</docs>
      <fields>
        <field name="Reference">U</field>
        <field name="Value">TPS73233DBVT</field>
        <field name="Footprint">SOT95P280X145-5N</field>
        <field name="Datasheet">1.02 USD</field>
        <field name="Field4">SOT-23-5 Texas Instruments</field>
        <field name="Field5">TPS73233DBVT</field>
        <field name="Field7">Texas Instruments</field>
        <field name="Field8">Cap-Free, NMOS, 250mA Low Dropout Regulator with Reverse Current Protection 5-SOT-23 -40 to 125</field>
      </fields>
      <pins>
        <pin num="1" name="IN" type="power_in"/>
        <pin num="2" name="GND" type="passive"/>
        <pin num="3" name="EN" type="input"/>
        <pin num="4" name="NR/FB" type="input"/>
        <pin num="5" name="OUT" type="output"/>
      </pins>
    </libpart>
    <libpart lib="badgelife_shitty_addon_v169bis" part="Badgelife_sao_connector_v169bis">
      <fields>
        <field name="Reference">X</field>
        <field name="Value">Badgelife_sao_connector_v169bis</field>
      </fields>
      <pins>
        <pin num="1" name="VCC" type="input"/>
        <pin num="2" name="GND" type="input"/>
        <pin num="3" name="SDA" type="input"/>
        <pin num="4" name="SCL" type="input"/>
        <pin num="5" name="GPIO1" type="input"/>
        <pin num="6" name="GPIO2" type="input"/>
      </pins>
    </libpart>
    <libpart lib="programmer-rescue" part="ATmega32U4-AU-MCU_Microchip_ATmega">
      <footprints>
        <fp>TQFP*10x10mm*P0.8mm*</fp>
      </footprints>
      <fields>
        <field name="Reference">U</field>
        <field name="Value">ATmega32U4-AU-MCU_Microchip_ATmega</field>
        <field name="Footprint">Package_QFP:TQFP-44_10x10mm_P0.8mm</field>
      </fields>
      <pins>
        <pin num="1" name="PE6" type="tri_state"/>
        <pin num="2" name="UVCC" type="power_in"/>
        <pin num="3" name="D-" type="bidirectional"/>
        <pin num="4" name="D+" type="bidirectional"/>
        <pin num="5" name="UGND" type="passive"/>
        <pin num="6" name="UCAP" type="passive"/>
        <pin num="7" name="VBUS" type="input"/>
        <pin num="8" name="PB0" type="tri_state"/>
        <pin num="9" name="PB1" type="tri_state"/>
        <pin num="10" name="PB2" type="tri_state"/>
        <pin num="11" name="PB3" type="tri_state"/>
        <pin num="12" name="PB7" type="tri_state"/>
        <pin num="13" name="~RESET" type="input"/>
        <pin num="14" name="VCC" type="power_in"/>
        <pin num="15" name="GND" type="power_in"/>
        <pin num="16" name="XTAL2" type="output"/>
        <pin num="17" name="XTAL1" type="input"/>
        <pin num="18" name="PD0" type="tri_state"/>
        <pin num="19" name="PD1" type="tri_state"/>
        <pin num="20" name="PD2" type="tri_state"/>
        <pin num="21" name="PD3" type="tri_state"/>
        <pin num="22" name="PD5" type="tri_state"/>
        <pin num="23" name="GND" type="passive"/>
        <pin num="24" name="AVCC" type="power_in"/>
        <pin num="25" name="PD4" type="tri_state"/>
        <pin num="26" name="PD6" type="tri_state"/>
        <pin num="27" name="PD7" type="tri_state"/>
        <pin num="28" name="PB4" type="tri_state"/>
        <pin num="29" name="PB5" type="tri_state"/>
        <pin num="30" name="PB6" type="tri_state"/>
        <pin num="31" name="PC6" type="tri_state"/>
        <pin num="32" name="PC7" type="tri_state"/>
        <pin num="33" name="~HWB~/PE2" type="tri_state"/>
        <pin num="34" name="VCC" type="passive"/>
        <pin num="35" name="GND" type="passive"/>
        <pin num="36" name="PF7" type="tri_state"/>
        <pin num="37" name="PF6" type="tri_state"/>
        <pin num="38" name="PF5" type="tri_state"/>
        <pin num="39" name="PF4" type="tri_state"/>
        <pin num="40" name="PF1" type="tri_state"/>
        <pin num="41" name="PF0" type="tri_state"/>
        <pin num="42" name="AREF" type="passive"/>
        <pin num="43" name="GND" type="passive"/>
        <pin num="44" name="AVCC" type="passive"/>
      </pins>
    </libpart>
    <libpart lib="programmer-rescue" part="Test_Point-Connector_Specialized">
      <footprints>
        <fp>Pin*</fp>
        <fp>Test*</fp>
      </footprints>
      <fields>
        <field name="Reference">TP</field>
        <field name="Value">Test_Point-Connector_Specialized</field>
      </fields>
      <pins>
        <pin num="1" name="1" type="passive"/>
      </pins>
    </libpart>
    <libpart lib="programmer-rescue" part="USB_B_Micro-Connector_Specialized">
      <footprints>
        <fp>USB*</fp>
      </footprints>
      <fields>
        <field name="Reference">J</field>
        <field name="Value">USB_B_Micro-Connector_Specialized</field>
      </fields>
      <pins>
        <pin num="1" name="VBUS" type="power_out"/>
        <pin num="2" name="D-" type="passive"/>
        <pin num="3" name="D+" type="passive"/>
        <pin num="4" name="ID" type="passive"/>
        <pin num="5" name="GND" type="power_out"/>
        <pin num="6" name="Shield" type="passive"/>
      </pins>
    </libpart>
  </libparts>
  <libraries>
    <library logical="Connector_Generic">
      <uri>C:\Program Files\KiCad\share\kicad\library/Connector_Generic.lib</uri>
    </library>
    <library logical="Device">
      <uri>C:\Program Files\KiCad\share\kicad\library/Device.lib</uri>
    </library>
    <library logical="Jumper">
      <uri>C:\Program Files\KiCad\share\kicad\library/Jumper.lib</uri>
    </library>
    <library logical="LED">
      <uri>C:\Program Files\KiCad\share\kicad\library/LED.lib</uri>
    </library>
    <library logical="Switch">
      <uri>C:\Program Files\KiCad\share\kicad\library/Switch.lib</uri>
    </library>
    <library logical="TPS73233DBVT">
      <uri>C:\Users\hamster\Documents\Development\dczia\Ziacon2/lib_sch/TPS73233DBVT.lib</uri>
    </library>
    <library logical="badgelife_shitty_addon_v169bis">
      <uri>C:\Users\hamster\Documents\Development\dczia\Ziacon2/lib_sch/badgelife_shitty_addon_v169bis.lib</uri>
    </library>
    <library logical="programmer-rescue">
      <uri>C:\Users\hamster\Documents\Development\dczia\Ziacon2/programmer-rescue.lib</uri>
    </library>
  </libraries>
  <nets>
    <net code="1" name="+5V">
      <node ref="C1" pin="1" pintype="passive"/>
      <node ref="J2" pin="1" pinfunction="VBUS" pintype="power_out"/>
      <node ref="U1" pin="1" pinfunction="IN" pintype="power_in"/>
      <node ref="U1" pin="3" pinfunction="EN" pintype="input"/>
      <node ref="U2" pin="2" pinfunction="UVCC" pintype="power_in"/>
      <node ref="U2" pin="7" pinfunction="VBUS" pintype="input"/>
    </net>
    <net code="2" name="BOB_IN">
      <node ref="D1" pin="4" pinfunction="DIN" pintype="input"/>
      <node ref="U2" pin="41" pinfunction="PF0" pintype="tri_state"/>
    </net>
    <net code="3" name="BOB_OUT">
      <node ref="D10" pin="2" pinfunction="DOUT" pintype="output"/>
      <node ref="X1" pin="6" pinfunction="GPIO2" pintype="input"/>
    </net>
    <net code="4" name="GND">
      <node ref="C1" pin="2" pintype="passive"/>
      <node ref="C2" pin="1" pintype="passive"/>
      <node ref="C3" pin="1" pintype="passive"/>
      <node ref="C4" pin="2" pintype="passive"/>
      <node ref="C5" pin="2" pintype="passive"/>
      <node ref="C6" pin="2" pintype="passive"/>
      <node ref="D1" pin="3" pinfunction="VSS" pintype="power_in"/>
      <node ref="D10" pin="3" pinfunction="VSS" pintype="power_in"/>
      <node ref="D2" pin="3" pinfunction="VSS" pintype="power_in"/>
      <node ref="D3" pin="3" pinfunction="VSS" pintype="power_in"/>
      <node ref="D4" pin="3" pinfunction="VSS" pintype="power_in"/>
      <node ref="D5" pin="3" pinfunction="VSS" pintype="power_in"/>
      <node ref="D6" pin="3" pinfunction="VSS" pintype="power_in"/>
      <node ref="D7" pin="3" pinfunction="VSS" pintype="power_in"/>
      <node ref="D8" pin="3" pinfunction="VSS" pintype="power_in"/>
      <node ref="D9" pin="3" pinfunction="VSS" pintype="power_in"/>
      <node ref="J1" pin="6" pinfunction="Pin_6" pintype="passive"/>
      <node ref="J2" pin="5" pinfunction="GND" pintype="power_out"/>
      <node ref="JP3" pin="2" pinfunction="B" pintype="passive"/>
      <node ref="SW1" pin="1" pinfunction="1" pintype="passive"/>
      <node ref="U1" pin="2" pinfunction="GND" pintype="passive"/>
      <node ref="U2" pin="15" pinfunction="GND" pintype="power_in"/>
      <node ref="U2" pin="23" pinfunction="GND" pintype="passive"/>
      <node ref="U2" pin="35" pinfunction="GND" pintype="passive"/>
      <node ref="U2" pin="43" pinfunction="GND" pintype="passive"/>
      <node ref="U2" pin="5" pinfunction="UGND" pintype="passive"/>
      <node ref="X1" pin="2" pinfunction="GND" pintype="input"/>
    </net>
    <net code="5" name="MISO">
      <node ref="J1" pin="1" pinfunction="Pin_1" pintype="passive"/>
      <node ref="U2" pin="11" pinfunction="PB3" pintype="tri_state"/>
    </net>
    <net code="6" name="MOSI">
      <node ref="J1" pin="4" pinfunction="Pin_4" pintype="passive"/>
      <node ref="U2" pin="10" pinfunction="PB2" pintype="tri_state"/>
    </net>
    <net code="7" name="Net-(C2-Pad2)">
      <node ref="C2" pin="2" pintype="passive"/>
      <node ref="U1" pin="4" pinfunction="NR/FB" pintype="input"/>
    </net>
    <net code="8" name="Net-(C4-Pad1)">
      <node ref="C4" pin="1" pintype="passive"/>
      <node ref="U2" pin="6" pinfunction="UCAP" pintype="passive"/>
    </net>
    <net code="9" name="Net-(C5-Pad1)">
      <node ref="C5" pin="1" pintype="passive"/>
      <node ref="U2" pin="17" pinfunction="XTAL1" pintype="input"/>
      <node ref="Y1" pin="2" pinfunction="2" pintype="passive"/>
    </net>
    <net code="10" name="Net-(C6-Pad1)">
      <node ref="C6" pin="1" pintype="passive"/>
      <node ref="U2" pin="16" pinfunction="XTAL2" pintype="output"/>
      <node ref="Y1" pin="1" pinfunction="1" pintype="passive"/>
    </net>
    <net code="11" name="Net-(D1-Pad2)">
      <node ref="D1" pin="2" pinfunction="DOUT" pintype="output"/>
      <node ref="D2" pin="4" pinfunction="DIN" pintype="input"/>
    </net>
    <net code="12" name="Net-(D2-Pad2)">
      <node ref="D2" pin="2" pinfunction="DOUT" pintype="output"/>
      <node ref="D3" pin="4" pinfunction="DIN" pintype="input"/>
    </net>
    <net code="13" name="Net-(D3-Pad2)">
      <node ref="D3" pin="2" pinfunction="DOUT" pintype="output"/>
      <node ref="D4" pin="4" pinfunction="DIN" pintype="input"/>
    </net>
    <net code="14" name="Net-(D4-Pad2)">
      <node ref="D4" pin="2" pinfunction="DOUT" pintype="output"/>
      <node ref="D5" pin="4" pinfunction="DIN" pintype="input"/>
    </net>
    <net code="15" name="Net-(D5-Pad2)">
      <node ref="D5" pin="2" pinfunction="DOUT" pintype="output"/>
      <node ref="D6" pin="4" pinfunction="DIN" pintype="input"/>
    </net>
    <net code="16" name="Net-(D6-Pad2)">
      <node ref="D6" pin="2" pinfunction="DOUT" pintype="output"/>
      <node ref="D7" pin="4" pinfunction="DIN" pintype="input"/>
    </net>
    <net code="17" name="Net-(D7-Pad2)">
      <node ref="D7" pin="2" pinfunction="DOUT" pintype="output"/>
      <node ref="D8" pin="4" pinfunction="DIN" pintype="input"/>
    </net>
    <net code="18" name="Net-(D8-Pad2)">
      <node ref="D8" pin="2" pinfunction="DOUT" pintype="output"/>
      <node ref="D9" pin="4" pinfunction="DIN" pintype="input"/>
    </net>
    <net code="19" name="Net-(D10-Pad4)">
      <node ref="D10" pin="4" pinfunction="DIN" pintype="input"/>
      <node ref="D9" pin="2" pinfunction="DOUT" pintype="output"/>
    </net>
    <net code="20" name="Net-(D11-Pad1)">
      <node ref="D11" pin="1" pinfunction="K" pintype="passive"/>
      <node ref="R6" pin="1" pintype="passive"/>
    </net>
    <net code="21" name="Net-(J2-Pad2)">
      <node ref="J2" pin="2" pinfunction="D-" pintype="passive"/>
      <node ref="R4" pin="2" pintype="passive"/>
    </net>
    <net code="22" name="Net-(J2-Pad3)">
      <node ref="J2" pin="3" pinfunction="D+" pintype="passive"/>
      <node ref="R3" pin="2" pintype="passive"/>
    </net>
    <net code="23" name="Net-(JP3-Pad1)">
      <node ref="JP3" pin="1" pinfunction="A" pintype="passive"/>
      <node ref="R7" pin="2" pintype="passive"/>
      <node ref="U2" pin="33" pinfunction="~HWB~/PE2" pintype="tri_state"/>
    </net>
    <net code="24" name="Net-(R3-Pad1)">
      <node ref="R3" pin="1" pintype="passive"/>
      <node ref="U2" pin="4" pinfunction="D+" pintype="bidirectional"/>
    </net>
    <net code="25" name="Net-(R4-Pad1)">
      <node ref="R4" pin="1" pintype="passive"/>
      <node ref="U2" pin="3" pinfunction="D-" pintype="bidirectional"/>
    </net>
    <net code="26" name="Net-(R6-Pad2)">
      <node ref="R6" pin="2" pintype="passive"/>
      <node ref="U2" pin="31" pinfunction="PC6" pintype="tri_state"/>
    </net>
    <net code="27" name="Net-(RX1-Pad1)">
      <node ref="RX1" pin="1" pinfunction="1" pintype="passive"/>
      <node ref="U2" pin="20" pinfunction="PD2" pintype="tri_state"/>
    </net>
    <net code="28" name="Net-(TX1-Pad1)">
      <node ref="TX1" pin="1" pinfunction="1" pintype="passive"/>
      <node ref="U2" pin="21" pinfunction="PD3" pintype="tri_state"/>
    </net>
    <net code="29" name="RST">
      <node ref="J1" pin="5" pinfunction="Pin_5" pintype="passive"/>
      <node ref="R5" pin="2" pintype="passive"/>
      <node ref="SW1" pin="2" pinfunction="2" pintype="passive"/>
      <node ref="U2" pin="13" pinfunction="~RESET" pintype="input"/>
    </net>
    <net code="30" name="SCK">
      <node ref="J1" pin="3" pinfunction="Pin_3" pintype="passive"/>
      <node ref="U2" pin="9" pinfunction="PB1" pintype="tri_state"/>
    </net>
    <net code="31" name="SCL">
      <node ref="U2" pin="18" pinfunction="PD0" pintype="tri_state"/>
      <node ref="X1" pin="4" pinfunction="SCL" pintype="input"/>
    </net>
    <net code="32" name="SDA">
      <node ref="U2" pin="19" pinfunction="PD1" pintype="tri_state"/>
      <node ref="X1" pin="3" pinfunction="SDA" pintype="input"/>
    </net>
    <net code="33" name="UPDI">
      <node ref="U2" pin="1" pinfunction="PE6" pintype="tri_state"/>
      <node ref="X1" pin="5" pinfunction="GPIO1" pintype="input"/>
    </net>
    <net code="34" name="VCC">
      <node ref="C3" pin="2" pintype="passive"/>
      <node ref="D1" pin="1" pinfunction="VDD" pintype="power_in"/>
      <node ref="D10" pin="1" pinfunction="VDD" pintype="power_in"/>
      <node ref="D11" pin="2" pinfunction="A" pintype="passive"/>
      <node ref="D2" pin="1" pinfunction="VDD" pintype="power_in"/>
      <node ref="D3" pin="1" pinfunction="VDD" pintype="power_in"/>
      <node ref="D4" pin="1" pinfunction="VDD" pintype="power_in"/>
      <node ref="D5" pin="1" pinfunction="VDD" pintype="power_in"/>
      <node ref="D6" pin="1" pinfunction="VDD" pintype="power_in"/>
      <node ref="D7" pin="1" pinfunction="VDD" pintype="power_in"/>
      <node ref="D8" pin="1" pinfunction="VDD" pintype="power_in"/>
      <node ref="D9" pin="1" pinfunction="VDD" pintype="power_in"/>
      <node ref="J1" pin="2" pinfunction="Pin_2" pintype="passive"/>
      <node ref="R5" pin="1" pintype="passive"/>
      <node ref="R7" pin="1" pintype="passive"/>
      <node ref="U1" pin="5" pinfunction="OUT" pintype="output"/>
      <node ref="U2" pin="14" pinfunction="VCC" pintype="power_in"/>
      <node ref="U2" pin="24" pinfunction="AVCC" pintype="power_in"/>
      <node ref="U2" pin="34" pinfunction="VCC" pintype="passive"/>
      <node ref="U2" pin="42" pinfunction="AREF" pintype="passive"/>
      <node ref="U2" pin="44" pinfunction="AVCC" pintype="passive"/>
      <node ref="X1" pin="1" pinfunction="VCC" pintype="input"/>
    </net>
    <net code="35" name="unconnected-(J2-Pad4)">
      <node ref="J2" pin="4" pinfunction="ID" pintype="passive"/>
    </net>
    <net code="36" name="unconnected-(J2-Pad6)">
      <node ref="J2" pin="6" pinfunction="Shield" pintype="passive"/>
    </net>
    <net code="37" name="unconnected-(U2-Pad8)">
      <node ref="U2" pin="8" pinfunction="PB0" pintype="tri_state"/>
    </net>
    <net code="38" name="unconnected-(U2-Pad12)">
      <node ref="U2" pin="12" pinfunction="PB7" pintype="tri_state"/>
    </net>
    <net code="39" name="unconnected-(U2-Pad22)">
      <node ref="U2" pin="22" pinfunction="PD5" pintype="tri_state"/>
    </net>
    <net code="40" name="unconnected-(U2-Pad25)">
      <node ref="U2" pin="25" pinfunction="PD4" pintype="tri_state"/>
    </net>
    <net code="41" name="unconnected-(U2-Pad26)">
      <node ref="U2" pin="26" pinfunction="PD6" pintype="tri_state"/>
    </net>
    <net code="42" name="unconnected-(U2-Pad27)">
      <node ref="U2" pin="27" pinfunction="PD7" pintype="tri_state"/>
    </net>
    <net code="43" name="unconnected-(U2-Pad28)">
      <node ref="U2" pin="28" pinfunction="PB4" pintype="tri_state"/>
    </net>
    <net code="44" name="unconnected-(U2-Pad29)">
      <node ref="U2" pin="29" pinfunction="PB5" pintype="tri_state"/>
    </net>
    <net code="45" name="unconnected-(U2-Pad30)">
      <node ref="U2" pin="30" pinfunction="PB6" pintype="tri_state"/>
    </net>
    <net code="46" name="unconnected-(U2-Pad32)">
      <node ref="U2" pin="32" pinfunction="PC7" pintype="tri_state"/>
    </net>
    <net code="47" name="unconnected-(U2-Pad36)">
      <node ref="U2" pin="36" pinfunction="PF7" pintype="tri_state"/>
    </net>
    <net code="48" name="unconnected-(U2-Pad37)">
      <node ref="U2" pin="37" pinfunction="PF6" pintype="tri_state"/>
    </net>
    <net code="49" name="unconnected-(U2-Pad38)">
      <node ref="U2" pin="38" pinfunction="PF5" pintype="tri_state"/>
    </net>
    <net code="50" name="unconnected-(U2-Pad39)">
      <node ref="U2" pin="39" pinfunction="PF4" pintype="tri_state"/>
    </net>
    <net code="51" name="unconnected-(U2-Pad40)">
      <node ref="U2" pin="40" pinfunction="PF1" pintype="tri_state"/>
    </net>
  </nets>
</export>
